task3/counter.sv
module counter #(
  parameter WIDTH = 8
)(
  // interface signals
  input  logic             clk,      // clock
  input  logic             rst,      // reset
  input  logic             ld,       // load counter from data
  input  logic [WIDTH-1:0] v,        // value to preload
  output logic [WIDTH-1:0] count     // count output
);

always_ff @ (posedge clk)
  if (rst) count <= { WIDTH{1'b0} };
  else     count <= ld ? v : count + { {WIDTH-1{1'b0} },1'b1};

endmodule

task3/counter.vcd
$version Generated by VerilatedVcd $end
$date Fri Oct 25 11:01:11 2024 $end
$timescale 1ps $end

 $scope module TOP $end
  $var wire  1 # clk $end
  $var wire  8 ' count [7:0] $end
  $var wire  1 % ld $end
  $var wire  1 $ rst $end
  $var wire  8 & v [7:0] $end
  $scope module counter $end
   $var wire 32 ( WIDTH [31:0] $end
   $var wire  1 # clk $end
   $var wire  8 ' count [7:0] $end
   $var wire  1 % ld $end
   $var wire  1 $ rst $end
   $var wire  8 & v [7:0] $end
  $upscope $end
 $upscope $end
$enddefinitions $end


#0
1#
1$
0%
b00101110 &
b00000000 '
b00000000000000000000000000001000 (
#1
0#
#2
1#
#3
0#
#4
1#
#5
0#
#6
1#
0$
#7
0#
#8
1#
b00000001 '
#9
0#
#10
1#
b00000010 '
#11
0#
#12
1#
b00000011 '
#13
0#
#14
1#
b00000100 '
#15
0#
#16
1#
b00000101 '
#17
0#
#18
1#
b00000110 '
#19
0#
#20
1#
b00000111 '
#21
0#
#22
1#
b00001000 '
#23
0#
#24
1#
b00001001 '
#25
0#
#26
1#
b00001010 '
#27
0#
#28
1#
b00001011 '
#29
0#
#30
1#
b00001100 '
#31
0#
#32
1#
1$
b00001101 '
#33
0#
#34
1#
0$
b00000000 '
#35
0#
#36
1#
b00000001 '
#37
0#
#38
1#
b00000010 '
#39
0#
#40
1#
b00000011 '
#41
0#
#42
1#
b00000100 '
#43
0#
#44
1#
b00000101 '
#45
0#
#46
1#
b00000110 '
#47
0#
#48
1#
b00000111 '
#49
0#
#50
1#
b00001000 '
#51
0#
#52
1#
b00001001 '
#53
0#
#54
1#
b00001010 '
#55
0#
#56
1#
b00001011 '
#57
0#
#58
1#
b00001100 '
#59
0#
#60
1#
b00001101 '
#61
0#
#62
1#
b00001110 '
#63
0#
#64
1#
b00001111 '
#65
0#
#66
1#
b00010000 '
#67
0#
#68
1#
b00010001 '
#69
0#
#70
1#
b00010010 '
#71
0#
#72
1#
b00010011 '
#73
0#
#74
1#
b00010100 '
#75
0#
#76
1#
b00010101 '
#77
0#
#78
1#
b00010110 '
#79
0#
#80
1#
b00010111 '
#81
0#
#82
1#
b00011000 '
#83
0#
#84
1#
b00011001 '
#85
0#
#86
1#
b00011010 '
#87
0#
#88
1#
b00011011 '
#89
0#
#90
1#
b00011100 '
#91
0#
#92
1#
b00011101 '
#93
0#
#94
1#
b00011110 '
#95
0#
#96
1#
b00011111 '
#97
0#
#98
1#
b00100000 '
#99
0#
#100
1#
b00100001 '
#101
0#
#102
1#
b00100010 '
#103
0#
#104
1#
b00100011 '
#105
0#
#106
1#
b00100100 '
#107
0#
#108
1#
b00100101 '
#109
0#
#110
1#
b00100110 '
#111
0#
#112
1#
b00100111 '
#113
0#
#114
1#
b00101000 '
#115
0#
#116
1#
b00101001 '
#117
0#
#118
1#
b00101010 '
#119
0#
#120
1#
b00101011 '
#121
0#
#122
1#
b00101100 '
#123
0#
#124
1#
b00101101 '
#125
0#
#126
1#
b00101110 '
#127
0#
#128
1#
b00101111 '
#129
0#
#130
1#
b00110000 '
#131
0#
#132
1#
b00110001 '
#133
0#
#134
1#
b00110010 '
#135
0#
#136
1#
b00110011 '
#137
0#
#138
1#
b00110100 '
#139
0#
#140
1#
b00110101 '
#141
0#
#142
1#
b00110110 '
#143
0#
#144
1#
b00110111 '
#145
0#
#146
1#
b00111000 '
#147
0#
#148
1#
b00111001 '
#149
0#
#150
1#
b00111010 '
#151
0#
#152
1#
b00111011 '
#153
0#
#154
1#
b00111100 '
#155
0#
#156
1#
b00111101 '
#157
0#
#158
1#
b00111110 '
#159
0#
#160
1#
b00111111 '
#161
0#
#162
1#
b01000000 '
#163
0#
#164
1#
b01000001 '
#165
0#
#166
1#
b01000010 '
#167
0#
#168
1#
b01000011 '
#169
0#
#170
1#
b01000100 '
#171
0#
#172
1#
b01000101 '
#173
0#
#174
1#
b01000110 '
#175
0#
#176
1#
b01000111 '
#177
0#
#178
1#
b01001000 '
#179
0#
#180
1#
b01001001 '
#181
0#
#182
1#
b01001010 '
#183
0#
#184
1#
b01001011 '
#185
0#
#186
1#
b01001100 '
#187
0#
#188
1#
b01001101 '
#189
0#
#190
1#
b01001110 '
#191
0#
#192
1#
b01001111 '
#193
0#
#194
1#
b01010000 '
#195
0#
#196
1#
b01010001 '
#197
0#
#198
1#
b01010010 '
#199
0#
#200
1#
b01010011 '
#201
0#
#202
1#
b01010100 '
#203
0#
#204
1#
b01010101 '
#205
0#
#206
1#
b01010110 '
#207
0#
#208
1#
b01010111 '
#209
0#
#210
1#
b01011000 '
#211
0#
#212
1#
b01011001 '
#213
0#
#214
1#
b01011010 '
#215
0#
#216
1#
b01011011 '
#217
0#
#218
1#
b01011100 '
#219
0#
#220
1#
b01011101 '
#221
0#
#222
1#
b01011110 '
#223
0#
#224
1#
b01011111 '
#225
0#
#226
1#
b01100000 '
#227
0#
#228
1#
b01100001 '
#229
0#
#230
1#
b01100010 '
#231
0#
#232
1#
b01100011 '
#233
0#
#234
1#
b01100100 '
#235
0#
#236
1#
b01100101 '
#237
0#
#238
1#
b01100110 '
#239
0#
#240
1#
b01100111 '
#241
0#
#242
1#
b00101101 &
b01101000 '
#243
0#
#244
1#
b00101100 &
b01101001 '
#245
0#
#246
1#
b01101010 '
#247
0#
#248
1#
b01101011 '
#249
0#
#250
1#
b01101100 '
#251
0#
#252
1#
b00101011 &
b01101101 '
#253
0#
#254
1#
b01101110 '
#255
0#
#256
1#
b01101111 '
#257
0#
#258
1#
b01110000 '
#259
0#
#260
1#
b00101010 &
b01110001 '
#261
0#
#262
1#
b01110010 '
#263
0#
#264
1#
b01110011 '
#265
0#
#266
1#
b01110100 '
#267
0#
#268
1#
b00101001 &
b01110101 '
#269
0#
#270
1#
b01110110 '
#271
0#
#272
1#
b01110111 '
#273
0#
#274
1#
b01111000 '
#275
0#
#276
1#
b01111001 '
#277
0#
#278
1#
b01111010 '
#279
0#
#280
1#
b00101000 &
b01111011 '
#281
0#
#282
1#
b01111100 '
#283
0#
#284
1#
b01111101 '
#285
0#
#286
1#
b01111110 '
#287
0#
#288
1#
b01111111 '
#289
0#
#290
1#
b10000000 '
#291
0#
#292
1#
b10000001 '
#293
0#
#294
1#
b10000010 '
#295
0#
#296
1#
b10000011 '
#297
0#
#298
1#
b10000100 '
#299
0#
#300
1#
b10000101 '
#301
0#
#302
1#
b10000110 '
#303
0#
#304
1#
b10000111 '
#305
0#
#306
1#
b10001000 '
#307
0#
#308
1#
b10001001 '
#309
0#
#310
1#
b10001010 '
#311
0#
#312
1#
b10001011 '
#313
0#
#314
1#
b10001100 '
#315
0#
#316
1#
b10001101 '
#317
0#
#318
1#
1%
b10001110 '
#319
0#
#320
1#
0%
b00101000 '
#321
0#
#322
1#
b00101001 '
#323
0#
#324
1#
b00101010 '
#325
0#
#326
1#
b00101011 '
#327
0#
#328
1#
b00101100 '
#329
0#
#330
1#
b00101101 '
#331
0#
#332
1#
b00101110 '
#333
0#
#334
1#
b00101111 '
#335
0#
#336
1#
b00110000 '
#337
0#
#338
1#
b00110001 '
#339
0#
#340
1#
b00110010 '
#341
0#
#342
1#
b00110011 '
#343
0#
#344
1#
b00110100 '
#345
0#
#346
1#
b00110101 '
#347
0#
#348
1#
b00110110 '
#349
0#
#350
1#
b00110111 '
#351
0#
#352
1#
b00111000 '
#353
0#
#354
1#
b00111001 '
#355
0#
#356
1#
b00111010 '
#357
0#
#358
1#
b00111011 '
#359
0#
#360
1#
b00111100 '
#361
0#
#362
1#
b00111101 '
#363
0#
#364
1#
b00111110 '
#365
0#
#366
1#
b00111111 '
#367
0#
#368
1#
b01000000 '
#369
0#
#370
1#
b01000001 '
#371
0#
#372
1#
b01000010 '
#373
0#
#374
1#
b01000011 '
#375
0#
#376
1#
b01000100 '
#377
0#
#378
1#
b01000101 '
#379
0#
#380
1#
b01000110 '
#381
0#
#382
1#
b01000111 '
#383
0#
#384
1#
b01001000 '
#385
0#
#386
1#
b01001001 '
#387
0#
#388
1#
b01001010 '
#389
0#
#390
1#
b01001011 '
#391
0#
#392
1#
b01001100 '
#393
0#
#394
1#
b01001101 '
#395
0#
#396
1#
b01001110 '
#397
0#
#398
1#
b01001111 '
#399
0#
#400
1#
b01010000 '
#401
0#
#402
1#
b01010001 '
#403
0#
#404
1#
b01010010 '
#405
0#
#406
1#
b01010011 '
#407
0#
#408
1#
b01010100 '
#409
0#
#410
1#
b01010101 '
#411
0#
#412
1#
b01010110 '
#413
0#
#414
1#
b01010111 '
#415
0#
#416
1#
b01011000 '
#417
0#
#418
1#
b01011001 '
#419
0#
#420
1#
b01011010 '
#421
0#
#422
1#
b01011011 '
#423
0#
#424
1#
b01011100 '
#425
0#
#426
1#
b01011101 '
#427
0#
#428
1#
b01011110 '
#429
0#
#430
1#
b01011111 '
#431
0#
#432
1#
b01100000 '
#433
0#
#434
1#
b01100001 '
#435
0#
#436
1#
b01100010 '
#437
0#
#438
1#
b01100011 '
#439
0#
#440
1#
b01100100 '
#441
0#
#442
1#
b00101010 &
b01100101 '
#443
0#
#444
1#
b00101100 &
b01100110 '
#445
0#
#446
1#
b01100111 '
#447
0#
#448
1#
b01101000 '
#449
0#
#450
1#
b01101001 '
#451
0#
#452
1#
b01101010 '
#453
0#
#454
1#
b00101101 &
b01101011 '
#455
0#
#456
1#
b01101100 '
#457
0#
#458
1#
b00101110 &
b01101101 '
#459
0#
#460
1#
b00110000 &
b01101110 '
#461
0#
#462
1#
b00110001 &
b01101111 '
#463
0#
#464
1#
b00110010 &
b01110000 '
#465
0#
#466
1#
b01110001 '
#467
0#
#468
1#
b01110010 '
#469
0#
#470
1#
b00110011 &
b01110011 '
#471
0#
#472
1#
b01110100 '
#473
0#
#474
1#
b01110101 '
#475
0#
#476
1#
b01110110 '
#477
0#
#478
1#
b01110111 '
#479
0#
#480
1#
b01111000 '
#481
0#
#482
1#
b01111001 '
#483
0#
#484
1#
b01111010 '
#485
0#
#486
1#
b01111011 '
#487
0#
#488
1#
b01111100 '
#489
0#
#490
1#
b01111101 '
#491
0#
#492
1#
b01111110 '
#493
0#
#494
1#
b01111111 '
#495
0#
#496
1#
b10000000 '
#497
0#
#498
1#
b10000001 '
#499
0#
#500
1#
b10000010 '
#501
0#
#502
1#
b10000011 '
#503
0#
#504
1#
b10000100 '
#505
0#
#506
1#
b10000101 '
#507
0#
#508
1#
b10000110 '
#509
0#
#510
1#
b10000111 '
#511
0#
#512
1#
b10001000 '
#513
0#
#514
1#
b10001001 '
#515
0#
#516
1#
b10001010 '
#517
0#
#518
1#
b10001011 '
#519
0#
#520
1#
b10001100 '
#521
0#
#522
1#
b10001101 '
#523
0#
#524
1#
b10001110 '
#525
0#
#526
1#
b10001111 '
#527
0#
#528
1#
b10010000 '
#529
0#
#530
1#
b10010001 '
#531
0#
#532
1#
b10010010 '
#533
0#
#534
1#
b10010011 '
#535
0#
#536
1#
b10010100 '
#537
0#
#538
1#
b10010101 '
#539
0#
#540
1#
b10010110 '
#541
0#
#542
1#
b10010111 '
#543
0#
#544
1#
b10011000 '
#545
0#
#546
1#
b10011001 '
#547
0#
#548
1#
1%
b10011010 '
#549
0#
#550
1#
0%
b00110011 '
#551
0#
#552
1#
b00110100 '
#553
0#
#554
1#
b00110101 '
#555
0#
#556
1#
b00110110 '
#557
0#
#558
1#
b00110111 '
#559
0#
#560
1#
b00111000 '
#561
0#
#562
1#
b00111001 '
#563
0#
#564
1#
b00111010 '
#565
0#
#566
1#
b00111011 '
#567
0#
#568
1#
b00111100 '
#569
0#
#570
1#
b00111101 '
#571
0#
#572
1#
b00111110 '
#573
0#
#574
1#
b00111111 '
#575
0#
#576
1#
b01000000 '
#577
0#
#578
1#
b01000001 '
#579
0#
#580
1#
b01000010 '
#581
0#
#582
1#
b01000011 '
#583
0#
#584
1#
b01000100 '
#585
0#
#586
1#
b01000101 '
#587
0#
#588
1#
b01000110 '
#589
0#
#590
1#
b01000111 '
#591
0#
#592
1#
b01001000 '
#593
0#
#594
1#
b01001001 '
#595
0#
#596
1#
b01001010 '
#597
0#
#598
1#
b01001011 '
